setup.py
backtest/___init___.py
backtest/backtest.py
backtest/charts.py
backtest/graphql_query.py
backtest/liquidity.py
backtest/uniswapV3.py
rand_uniswap_yield.egg-info/PKG-INFO
rand_uniswap_yield.egg-info/SOURCES.txt
rand_uniswap_yield.egg-info/dependency_links.txt
rand_uniswap_yield.egg-info/requires.txt
rand_uniswap_yield.egg-info/top_level.txt