Metadata-Version: 2.1
Name: rand-uniswap-yield
Version: 2.2.2
Summary: A python library for Uniswap yield startegies
Home-page: https://github.com/Rand-Network/yield-strategy-data
Author: adradr
Author-email: adrian@rand.network
License: MIT license
Keywords: uniswap amm defi yield strategy backtest simulate
Requires-Python: >=3.7
